ffbinaries/__init__.py
ffbinaries/api.py
ffbinaries/enums.py
ffbinaries/exceptions.py
ffbinaries/utils.py
ffbinaries/schemas/__init__.py
ffbinaries/schemas/version.py
ffbinaries_api_client-0.0.21.dist-info/licenses/LICENSE
ffbinaries_api_client-0.0.21.dist-info/METADATA
ffbinaries_api_client-0.0.21.dist-info/WHEEL
ffbinaries_api_client-0.0.21.dist-info/top_level.txt
ffbinaries_api_client-0.0.21.dist-info/RECORD
