Metadata-Version: 2.4
Name: ffbinaries-api-client
Version: 0.0.21
Summary: FFbinaries API Client
Project-URL: Repository, https://github.com/tropicoo/ffbinaries-api-client.git
Project-URL: Issues, https://github.com/tropicoo/ffbinaries-api-client/issues
Keywords: ffbinaries,ffmpeg,ffprobe,ffplay,ffserver,ffbinaries-api-client
Classifier: Development Status :: 4 - Beta
Classifier: Programming Language :: Python
Requires-Python: >=3.11
License-File: LICENSE
Requires-Dist: pydantic>=2.10.6
Requires-Dist: requests>=2.32.3
Dynamic: license-file
